{
	"id": "http://json-schema.org/schemas/TVClip.json",
	"title": "TV Clip",
	"format": "http://schema.org/TVClip",
	"allOf": [{"$ref": "Clip.json"}],
	"type": "object",
	"properties": {"partOfTVSeries": {"$ref": "TVSeries.json#/definitions/possibleRef"}},
	"definitions": {
		"array": {
			"type": "array",
			"items": {"$ref": "#"}
		},
		"possibleRef": {
			"oneOf": [
				{"$ref": "#"},
				{
					"type": "string",
					"format": "uri",
					"links": [{
						"rel": "full",
						"href": "{+$}"
					}]
				}
			]
		},
		"possibleRefArray": {
			"type": "array",
			"items": {"$ref": "#/definitions/possibleRefArray"}
		}
	}
}